epub_translate/__init__.py
epub_translate/cli.py
epub_translate/config.py
epub_translate/translator.py
epub_translate-0.0.1.dist-info/LICENSE
epub_translate-0.0.1.dist-info/METADATA
epub_translate-0.0.1.dist-info/WHEEL
epub_translate-0.0.1.dist-info/entry_points.txt
epub_translate-0.0.1.dist-info/RECORD
