Metadata-Version: 2.3
Name: epub-translate
Version: 0.0.1
Summary: Simple cli tool for translating ebooks in EPUB format into any language.
License: MIT
Keywords: epub,ebook,translate,cli,translation,translator
Author: SpaceShaman
Author-email: spaceshaman@tuta.io
Requires-Python: >=3.10.0,<4.0.0
Classifier: License :: OSI Approved :: MIT License
Classifier: Programming Language :: Python :: 3
Classifier: Programming Language :: Python :: 3.10
Classifier: Programming Language :: Python :: 3.11
Classifier: Programming Language :: Python :: 3.12
Classifier: Programming Language :: Python :: 3.13
Requires-Dist: ebooklib (>=0.19,<0.20)
Requires-Dist: openai (>=1.82.0,<2.0.0)
Requires-Dist: tqdm (>=4.67.1,<5.0.0)
Requires-Dist: typer (>=0.16.0,<0.17.0)
Project-URL: Homepage, https://github.com/SpaceShaman/epub-translate
Project-URL: Repository, https://github.com/SpaceShaman/epub-translate
